setup.cfg
setup.py
bitcoin/__init__.py
bitcoin/interfaces.py
bitcoin/nets.py
bitcoin/units.py
bitcoin/address/__init__.py
bitcoin/address/model.py
bitcoin/address/p2pkh.py
bitcoin/address/p2sh.py
bitcoin/address/prefix.py
bitcoin/address/test.py
bitcoin/address/types.py
bitcoin/address/wif.py
bitcoin/crypto/__init__.py
bitcoin/crypto/ecdsa/__init__.py
bitcoin/crypto/ecdsa/calculator.py
bitcoin/crypto/ecdsa/curve.py
bitcoin/crypto/ecdsa/defaults.py
bitcoin/crypto/ecdsa/operations.py
bitcoin/crypto/ecdsa/secp256k1.py
bitcoin/crypto/hash/__init__.py
bitcoin/crypto/hash/operations.py
bitcoin/field/__init__.py
bitcoin/field/general.py
bitcoin/field/helper.py
bitcoin/field/model.py
bitcoin/field/opcode.py
bitcoin/field/script.py
bitcoin/field/test.py
bitcoin/io/__init__.py
bitcoin/io/model.py
bitcoin/io/input/__init__.py
bitcoin/io/input/model.py
bitcoin/io/output/__init__.py
bitcoin/io/output/model.py
bitcoin/io/output/test.py
bitcoin/script/__init__.py
bitcoin/script/model.py
bitcoin/script/pay/__init__.py
bitcoin/script/pay/model.py
bitcoin/script/pay/multisig.py
bitcoin/script/pay/timed.py
bitcoin/script/pubkey/__init__.py
bitcoin/script/pubkey/model.py
bitcoin/script/pubkey/p2pkh.py
bitcoin/script/pubkey/p2sh.py
bitcoin/script/redeem/__init__.py
bitcoin/script/redeem/model.py
bitcoin/script/redeem/multisig.py
bitcoin/script/redeem/timed.py
bitcoin/script/sig/__init__.py
bitcoin/script/sig/model.py
bitcoin/script/sig/p2pkh.py
bitcoin/script/sig/p2sh.py
bitcoin/tx/__init__.py
bitcoin/tx/model.py
bitcoin/tx/sign.py
bitcoin/tx/test.py
bitcoin_framework.egg-info/PKG-INFO
bitcoin_framework.egg-info/SOURCES.txt
bitcoin_framework.egg-info/dependency_links.txt
bitcoin_framework.egg-info/requires.txt
bitcoin_framework.egg-info/top_level.txt